<?xml version="1.0" encoding="UTF-8"?>
<prefab>
  <property name="CopyAirBlocks" value="True" />
  <property name="ExcludeDistantPOIMesh" value="False" />
  <property name="ExcludePOICulling" value="False" />
  <property name="DistantPOIYOffset" value="0" />
  <property name="AllowTopSoilDecorations" value="False" />
  <property name="DifficultyTier" value="0" />
  <property name="ShowQuestClearCount" value="1" />
  <property name="TraderArea" value="False" />
  <property name="YOffset" value="-1" />
  <property name="RotationToFaceNorth" value="2" />
  <property name="Zoning" value="none" />
  <property name="POIMarkerSize" value="7, 13, 1#7, 13, 1" />
  <property name="POIMarkerStart" value="5, 0, -1#13, 0, -1" />
  <property name="POIMarkerGroup" value="driveway,driveway2" />
  <property name="POIMarkerTags" value="industrial#industrial" />
  <property name="POIMarkerType" value="PartSpawn,PartSpawn" />
  <property name="POIMarkerPartToSpawn" value="part_driveway_industrial_01,part_driveway_industrial_01" />
  <property name="POIMarkerPartRotations" value="2,2" />
  <property name="POIMarkerPartSpawnChance" value="1,1" />
  <property name="SleeperVolumeSize" value="3, 3, 11#11, 5, 7#3, 3, 11" />
  <property name="SleeperVolumeStart" value="7, 2, 2#6, 2, 14#2, 1, 12" />
  <property name="SleeperVolumeGroupId" value="0,0,0" />
  <property name="SleeperVolumeGroup" value="GroupGenericZombie,1,1,GroupGenericZombie,1,1,GroupGenericZombie,1,1" />
  <property name="SleeperIsLootVolume" value="False,False,False" />
  <property name="SleeperIsQuestExclude" value="False,False,False" />
  <property name="SleeperVolumeFlags" value="0,0,0" />
  <property name="PrefabSize" value="25, 10, 25" />
  <property name="SleeperVolumeTriggeredBy" value=" # # " />
  <property name="Tags" value="industrial" />
  <property class="IndexedBlockOffsets">
    <property class="TraderOnOff">
      <property name="0" value="14, 2, 13" />
      <property name="1" value="17, 2, 19" />
    </property>
    <property class="challenge_pallet">
      <property name="0" value="8, 2, 16" />
    </property>
    <property class="POILight">
      <property name="0" value="14, 5, 17" />
      <property name="1" value="16, 4, 19" />
      <property name="2" value="18, 5, 19" />
    </property>
  </property>
  <property class="Stats">
    <property name="TotalVertices" value="99418" />
    <property name="TotalTriangles" value="37087" />
    <property class="BlockEntities">
      <property name="Vertices" value="81605" />
      <property name="Triangles" value="24519" />
    </property>
    <property class="ChunkMeshes0">
      <property name="Vertices" value="15945" />
      <property name="Triangles" value="9584" />
    </property>
    <property class="ChunkMeshes1">
      <property name="Vertices" value="0" />
      <property name="Triangles" value="0" />
    </property>
    <property class="ChunkMeshes2">
      <property name="Vertices" value="312" />
      <property name="Triangles" value="288" />
    </property>
    <property class="ChunkMeshes3">
      <property name="Vertices" value="0" />
      <property name="Triangles" value="0" />
    </property>
    <property class="ChunkMeshes4">
      <property name="Vertices" value="0" />
      <property name="Triangles" value="0" />
    </property>
    <property class="ChunkMeshes5">
      <property name="Vertices" value="1556" />
      <property name="Triangles" value="2696" />
    </property>
  </property>
</prefab>